LICENSE
colibrie/__init__.py
colibrie/core.py
colibrie/extract_tables.py
colibrie/geometry.py
colibrie/geometry_operation.py
colibrie/intersection.py
colibrie/segments.py
colibrie/tables.py
colibrie/utils.py
colibrie-1.2.dist-info/LICENSE
colibrie-1.2.dist-info/WHEEL
colibrie-1.2.dist-info/METADATA
colibrie-1.2.dist-info/RECORD
